python_source_ast_analyzer_devlibx/__init__.py
python_source_ast_analyzer_devlibx/cli.py
python_source_ast_analyzer_devlibx/utils.py
python_source_ast_analyzer_devlibx/graph/__init__.py
python_source_ast_analyzer_devlibx/graph/call_graph.py
python_source_ast_analyzer_devlibx/graph/graph_builder.py
python_source_ast_analyzer_devlibx/output/__init__.py
python_source_ast_analyzer_devlibx/output/formatters.py
python_source_ast_analyzer_devlibx/parser/__init__.py
python_source_ast_analyzer_devlibx/parser/ast_visitor.py
python_source_ast_analyzer_devlibx/parser/parser.py
python_source_ast_analyzer_devlibx/query/__init__.py
python_source_ast_analyzer_devlibx/query/query_engine.py
python_source_ast_analyzer_devlibx/server/__init__.py
python_source_ast_analyzer_devlibx/server/server.py
python_source_ast_analyzer_devlibx-0.1.0.dist-info/licenses/LICENSE
python_source_ast_analyzer_devlibx-0.1.0.dist-info/METADATA
python_source_ast_analyzer_devlibx-0.1.0.dist-info/WHEEL
python_source_ast_analyzer_devlibx-0.1.0.dist-info/entry_points.txt
python_source_ast_analyzer_devlibx-0.1.0.dist-info/top_level.txt
python_source_ast_analyzer_devlibx-0.1.0.dist-info/RECORD
