Metadata-Version: 2.4
Name: python-source-ast-analyzer-devlibx
Version: 0.1.0
Summary: A tool for analyzing Python source code using AST to generate call graphs
Author-email: DevLibX <info@devlibx.com>
License: MIT
Project-URL: Homepage, https://github.com/devlibx/python-source-ast-analyzer
Project-URL: Bug Tracker, https://github.com/devlibx/python-source-ast-analyzer/issues
Keywords: ast,static analysis,call graph,python
Classifier: Development Status :: 3 - Alpha
Classifier: Intended Audience :: Developers
Classifier: License :: OSI Approved :: MIT License
Classifier: Programming Language :: Python :: 3
Classifier: Programming Language :: Python :: 3.8
Classifier: Programming Language :: Python :: 3.9
Classifier: Programming Language :: Python :: 3.10
Classifier: Programming Language :: Python :: 3.11
Classifier: Topic :: Software Development :: Libraries :: Python Modules
Classifier: Topic :: Software Development :: Quality Assurance
Requires-Python: >=3.8
License-File: LICENSE
Requires-Dist: networkx>=2.6.0
Requires-Dist: flask>=2.0.0
Requires-Dist: requests>=2.25.0
Dynamic: license-file
